{
  "type" : "function",
  "step" : {
    "type" : "scope",
    "children" : [ {
      "type" : "click-element",
      "sources" : {
        "element" : {
          "type" : "element-linktext",
          "source" : {
            "value" : "Form Authentication",
            "type" : "string"
          }
        }
      },
      "metadata" : {
        "id" : 92625388830749
      }
    }, {
      "type" : "wait",
      "sources" : {
        "condition" : {
          "type" : "exists",
          "source" : {
            "type" : "page-element",
            "sourceMap" : {
              "page" : {
                "value" : "login-page",
                "type" : "string"
              },
              "element" : {
                "value" : "username",
                "type" : "string"
              }
            }
          }
        }
      },
      "metadata" : {
        "id" : 92625388830750
      }
    }, {
      "type" : "send-keys",
      "sources" : {
        "keys" : {
          "type" : "variable",
          "source" : {
            "value" : "username",
            "type" : "string"
          }
        },
        "clear" : {
          "value" : true,
          "type" : "boolean"
        },
        "element" : {
          "type" : "page-element",
          "sourceMap" : {
            "page" : {
              "value" : "login-page",
              "type" : "string"
            },
            "element" : {
              "value" : "username",
              "type" : "string"
            }
          }
        }
      },
      "metadata" : {
        "id" : 92625388830751
      }
    }, {
      "type" : "send-keys",
      "sources" : {
        "keys" : {
          "type" : "variable",
          "source" : {
            "value" : "password",
            "type" : "string"
          }
        },
        "clear" : {
          "value" : true,
          "type" : "boolean"
        },
        "element" : {
          "type" : "page-element",
          "sourceMap" : {
            "page" : {
              "value" : "login-page",
              "type" : "string"
            },
            "element" : {
              "value" : "password",
              "type" : "string"
            }
          }
        }
      },
      "metadata" : {
        "id" : 92625388830752
      }
    }, {
      "type" : "submit-element",
      "sources" : {
        "element" : {
          "type" : "page-element",
          "sourceMap" : {
            "page" : {
              "value" : "login-page",
              "type" : "string"
            },
            "element" : {
              "value" : "login-form",
              "type" : "string"
            }
          }
        }
      },
      "metadata" : {
        "id" : 92625388830753
      }
    }, {
      "type" : "wait",
      "sources" : {
        "condition" : {
          "type" : "exists",
          "source" : {
            "type" : "page-element",
            "sourceMap" : {
              "page" : {
                "value" : "login-page",
                "type" : "string"
              },
              "element" : {
                "value" : "content-section",
                "type" : "string"
              }
            }
          }
        }
      },
      "metadata" : {
        "id" : 92625388830754
      }
    } ],
    "metadata" : {
      "id" : 92625388830748
    }
  },
  "tags" : [ ]
}